{"GlobalPropertiesHash":"EjM8lklIOavgnJvAJcrKoQerL83cqmP2lf82/C3sQVY=","FingerprintPatternsHash":"gq3WsqcKBUGTSNle7RKKyXRIwh7M8ccEqOqYvIzoM04=","PropertyOverridesHash":"8ZRc1sGeVrPBx4lD717BgRaQekyh78QKV9SKsdt638U=","InputHashes":["byU1HRqGirN0BM74MeJBSYCTNh8hu6Ya0vbu2T3Nz6k=","68wpOqYQUIhmsO9WJT3Ky2/xYkJxJlxApKOHYUiyGYw=","h13bXbG7pBK52sQUm6m6E5B6gt\u002BkQnC\u002BqJ1kNHYH\u002Bmo=","8sTmvKgZM3iVBRKwSL3TjeXxMozEMwnKJRuD8hmiKWw=","x/X1mYF53x7YJ/owKrHaLBdUFN1P74EyN37vPTljW3s=","DM5mgR32ZDySOzrvHJMMKy5X1cLO7JE0yQUoNRA\u002BWcY=","lD3626M6UoCwg3rMpQhA882ulULnLPAyvOANnmO9X3Q=","bdzkeha3/YiWLLX0cH1dTBViCxCMONUisv3Sn829upo=","gGXJiqFg4KWVlx4RI43kssWEP9eBXIOBoAEiuBaSZio=","t9/EvUher6L/zYBnDp5ynzt\u002B\u002B\u002BZzJVzGz7ISUF1rlTE=","hmbXGcAH7WqXyUpPZsTiuyU7xLriApgiypUm8n4OUZQ=","yC4a02rCnW3bymmbB3oMFsc725ZlVA/vXUnmGoxWkZA=","W\u002Bz6vphfifAYfLJsOg0d5x26hwkwHxN8gMDBn66Oy9A=","sHn4Y2ceiyQhKyxF4FHzKVIqQlb7lVrWdFzAHqxAcUs=","PJbkqqTXp8cl27tBIqWzcP7KhewDOAIFqcKX9mHoi3g="],"CachedAssets":{"byU1HRqGirN0BM74MeJBSYCTNh8hu6Ya0vbu2T3Nz6k=":{"Identity":"C:\\Users\\mgmal\\source\\repos\\TestTypingSpeeds\\wwwroot\\app.css","SourceId":"TestTypingSpeeds","SourceType":"Discovered","ContentRoot":"C:\\Users\\mgmal\\source\\repos\\TestTypingSpeeds\\wwwroot\\","BasePath":"_content/TestTypingSpeeds","RelativePath":"app#[.{fingerprint}]?.css","AssetKind":"All","AssetMode":"All","AssetRole":"Primary","AssetMergeBehavior":null,"AssetMergeSource":"","RelatedAsset":null,"AssetTraitName":null,"AssetTraitValue":null,"Fingerprint":"da95v2qkru","Integrity":"u9qEka1auR7E3rd3/8/j8hkQdSOYj9bRJ4nYiFDR1sE=","CopyToOutputDirectory":"Never","CopyToPublishDirectory":"PreserveNewest","OriginalItemSpec":"wwwroot\\app.css","FileLength":2591,"LastWriteTime":"2026-02-22T20:20:33.6194993+00:00"},"68wpOqYQUIhmsO9WJT3Ky2/xYkJxJlxApKOHYUiyGYw=":{"Identity":"C:\\Users\\mgmal\\source\\repos\\TestTypingSpeeds\\wwwroot\\bootstrap\\bootstrap.min.css","SourceId":"TestTypingSpeeds","SourceType":"Discovered","ContentRoot":"C:\\Users\\mgmal\\source\\repos\\TestTypingSpeeds\\wwwroot\\","BasePath":"_content/TestTypingSpeeds","RelativePath":"bootstrap/bootstrap.min#[.{fingerprint}]?.css","AssetKind":"All","AssetMode":"All","AssetRole":"Primary","AssetMergeBehavior":null,"AssetMergeSource":"","RelatedAsset":null,"AssetTraitName":null,"AssetTraitValue":null,"Fingerprint":"bpk8xqwxhs","Integrity":"z8OR40MowJ8GgK6P89Y\u002BhiJK5\u002BcclzFHzLhFQLL92bg=","CopyToOutputDirectory":"Never","CopyToPublishDirectory":"PreserveNewest","OriginalItemSpec":"wwwroot\\bootstrap\\bootstrap.min.css","FileLength":162720,"LastWriteTime":"2026-02-22T20:20:33.7112879+00:00"},"h13bXbG7pBK52sQUm6m6E5B6gt\u002BkQnC\u002BqJ1kNHYH\u002Bmo=":{"Identity":"C:\\Users\\mgmal\\source\\repos\\TestTypingSpeeds\\wwwroot\\bootstrap\\bootstrap.min.css.map","SourceId":"TestTypingSpeeds","SourceType":"Discovered","ContentRoot":"C:\\Users\\mgmal\\source\\repos\\TestTypingSpeeds\\wwwroot\\","BasePath":"_content/TestTypingSpeeds","RelativePath":"bootstrap/bootstrap.min.css#[.{fingerprint}]?.map","AssetKind":"All","AssetMode":"All","AssetRole":"Primary","AssetMergeBehavior":null,"AssetMergeSource":"","RelatedAsset":null,"AssetTraitName":null,"AssetTraitValue":null,"Fingerprint":"8inm30yfxf","Integrity":"gBwg2tmA0Ci2u54gMF1jNCVku6vznarkLS6D76htNNQ=","CopyToOutputDirectory":"Never","CopyToPublishDirectory":"PreserveNewest","OriginalItemSpec":"wwwroot\\bootstrap\\bootstrap.min.css.map","FileLength":449111,"LastWriteTime":"2026-02-22T20:20:33.712287+00:00"},"8sTmvKgZM3iVBRKwSL3TjeXxMozEMwnKJRuD8hmiKWw=":{"Identity":"C:\\Users\\mgmal\\source\\repos\\TestTypingSpeeds\\wwwroot\\favicon.png","SourceId":"TestTypingSpeeds","SourceType":"Discovered","ContentRoot":"C:\\Users\\mgmal\\source\\repos\\TestTypingSpeeds\\wwwroot\\","BasePath":"_content/TestTypingSpeeds","RelativePath":"favicon#[.{fingerprint}]?.png","AssetKind":"All","AssetMode":"All","AssetRole":"Primary","AssetMergeBehavior":null,"AssetMergeSource":"","RelatedAsset":null,"AssetTraitName":null,"AssetTraitValue":null,"Fingerprint":"ifv42okdf2","Integrity":"4mWsDy3aHl36ZbGt8zByK7Pvd4kRUoNgTYzRnwmPHwg=","CopyToOutputDirectory":"Never","CopyToPublishDirectory":"PreserveNewest","OriginalItemSpec":"wwwroot\\favicon.png","FileLength":1148,"LastWriteTime":"2026-02-22T20:20:33.6194993+00:00"}},"CachedCopyCandidates":{}}